logtracer/__init__.py
LogTracer-0.1.0.dist-info/LICENSE
LogTracer-0.1.0.dist-info/METADATA
LogTracer-0.1.0.dist-info/WHEEL
LogTracer-0.1.0.dist-info/top_level.txt
LogTracer-0.1.0.dist-info/RECORD
