Metadata-Version: 2.1
Name: LogTracer
Version: 0.1.0
Summary: Tracer util allowing masking of arguments in the log
Home-page: https://github.com/tbjorch/LogTracer
Author: Tobias Björch
License: UNKNOWN
Platform: UNKNOWN
